ElegooSmartCarController/__init__.py
ElegooSmartCarController/arduino_car_controller.py
ElegooSmartCarController-0.1.0.dist-info/METADATA
ElegooSmartCarController-0.1.0.dist-info/WHEEL
ElegooSmartCarController-0.1.0.dist-info/top_level.txt
ElegooSmartCarController-0.1.0.dist-info/RECORD
