Metadata-Version: 2.1
Name: ElegooSmartCarController
Version: 0.1.0
Summary: A Python library to control Elegoo Smart Car V4
Home-page: https://github.com/yourgithub/ElegooSmartCarController
Author: Frederick Feraco
Author-email: frederick.feraco@gmail.com
Classifier: Programming Language :: Python :: 3
Classifier: License :: OSI Approved :: MIT License
Classifier: Operating System :: OS Independent
Requires-Python: >=3.6
